{
    "MEGCoordinateSystem": "ElektaNeuromag",
    "MEGCoordinateUnits": "m",
    "MEGCoordinateSystemDescription": "RAS orientation and the origin between the ears",
    "HeadCoilCoordinates": {
        "NAS": [
            -1.4901161193847656e-08,
            0.08881056308746338,
            0.0
        ],
        "LPA": [
            -0.07580909132957458,
            2.9802322387695312e-08,
            1.1175870895385742e-08
        ],
        "RPA": [
            0.07547664642333984,
            0.0,
            1.4901161193847656e-08
        ],
        "coil1": [
            -0.0685645341873169,
            0.047099098563194275,
            0.09304207563400269
        ],
        "coil2": [
            -0.06994108855724335,
            -0.03319801390171051,
            0.10728073120117188
        ],
        "coil3": [
            0.06342905014753342,
            0.05513918399810791,
            0.09095900505781174
        ],
        "coil4": [
            0.06706629693508148,
            -0.031042814254760742,
            0.10974983870983124
        ]
    },
    "HeadCoilCoordinateSystem": "ElektaNeuromag",
    "HeadCoilCoordinateUnits": "m",
    "AnatomicalLandmarkCoordinates": {
        "NAS": [
            -1.4901161193847656e-08,
            0.08881056308746338,
            0.0
        ],
        "LPA": [
            -0.07580909132957458,
            2.9802322387695312e-08,
            1.1175870895385742e-08
        ],
        "RPA": [
            0.07547664642333984,
            0.0,
            1.4901161193847656e-08
        ]
    },
    "AnatomicalLandmarkCoordinateSystem": "ElektaNeuromag",
    "AnatomicalLandmarkCoordinateUnits": "m"
}
